pyconfig/__init__.py
pyconfig/scripts.py
pyconfig-3.2.3.dist-info/METADATA
pyconfig-3.2.3.dist-info/RECORD
pyconfig-3.2.3.dist-info/WHEEL
pyconfig-3.2.3.dist-info/entry_points.txt
pyconfig-3.2.3.dist-info/top_level.txt
